LICENSE
MANIFEST.in
README.rst
setup.py
docs/Makefile
docs/byrjunarskref.rst
docs/conf.py
docs/index.rst
docs/kodi.rst
docs/uppsetning.rst
korta/__init__.py
korta/client.py
korta/compat.py
korta/datastructures.py
korta/defaults.py
korta/tests.py
korta.egg-info/PKG-INFO
korta.egg-info/SOURCES.txt
korta.egg-info/dependency_links.txt
korta.egg-info/requires.txt
korta.egg-info/top_level.txt