Metadata-Version: 1.0
Name: korta
Version: 0.1.4.2
Summary: Korta Client library
Home-page: UNKNOWN
Author: Stefan Kjartansson
Author-email: esteban.supreme@gmail.com
License: UNKNOWN
Platform: UNKNOWN
Classifier: Development Status :: 4 - Beta
Classifier: Environment :: Web Environment
Classifier: Intended Audience :: Developers
Classifier: License :: OSI Approved :: MIT License
Classifier: Operating System :: OS Independent
Classifier: Programming Language :: Python
